pointextract/__init__.py
pointextract/main.py
pointextract-0.1.2.dist-info/LICENSE
pointextract-0.1.2.dist-info/METADATA
pointextract-0.1.2.dist-info/WHEEL
pointextract-0.1.2.dist-info/top_level.txt
pointextract-0.1.2.dist-info/RECORD
