Metadata-Version: 2.1
Name: pointextract
Version: 0.1.2
Summary: Polar to cartesian transforms using annular point sampling.
Author-email: Thomas Ciardi <thomas.ciardi@case.edu>, "Roger H. French" <rxf131@case.edu>
License: BSD 3-Clause License
Project-URL: Source Code, https://github.com/cwru-sdle/pointextract
Project-URL: Bug Tracker, https://github.com/cwru-sdle/pointextract/issues
Classifier: Programming Language :: Python :: 3
Classifier: License :: OSI Approved :: BSD License
Classifier: Operating System :: OS Independent
Requires-Python: >=3.9
License-File: LICENSE
Requires-Dist: numpy
Requires-Dist: scikit-image
Provides-Extra: test
Requires-Dist: pytest ; extra == 'test'
